elastic_agent_client/__init__.py
elastic_agent_client/client.py
elastic_agent_client/reader.py
elastic_agent_client/version.py
elastic_agent_client/examples/__init__.py
elastic_agent_client/examples/fake/__init__.py
elastic_agent_client/examples/fake/component.py
elastic_agent_client/generated/__init__.py
elastic_agent_client/generated/elastic_agent_client_deprecated_pb2.py
elastic_agent_client/generated/elastic_agent_client_deprecated_pb2.pyi
elastic_agent_client/generated/elastic_agent_client_deprecated_pb2_grpc.py
elastic_agent_client/generated/elastic_agent_client_future_pb2.py
elastic_agent_client/generated/elastic_agent_client_future_pb2.pyi
elastic_agent_client/generated/elastic_agent_client_future_pb2_grpc.py
elastic_agent_client/generated/elastic_agent_client_pb2.py
elastic_agent_client/generated/elastic_agent_client_pb2.pyi
elastic_agent_client/generated/elastic_agent_client_pb2_grpc.py
elastic_agent_client/handler/__init__.py
elastic_agent_client/handler/action.py
elastic_agent_client/handler/checkin.py
elastic_agent_client/service/__init__.py
elastic_agent_client/service/actions.py
elastic_agent_client/service/checkin.py
elastic_agent_client/util/__init__.py
elastic_agent_client/util/async_tools.py
elastic_agent_client/util/logger.py
elastic_agent_client-0.0.1.dev2.dist-info/METADATA
elastic_agent_client-0.0.1.dev2.dist-info/WHEEL
elastic_agent_client-0.0.1.dev2.dist-info/licenses/LICENSE
elastic_agent_client-0.0.1.dev2.dist-info/licenses/NOTICE.txt
elastic_agent_client-0.0.1.dev2.dist-info/RECORD
