Metadata-Version: 2.3
Name: elastic_agent_client
Version: 0.0.1.dev2
Summary: A python implementation of an Elastic Agent Client
Author-email: Search Extract and Transform Team <enterprise-search-ingestion-team@elastic.co>
License: Elastic V2
License-File: LICENSE
License-File: NOTICE.txt
Classifier: License :: Other/Proprietary License
Classifier: Programming Language :: Python
Classifier: Programming Language :: Python :: 3 :: Only
Classifier: Programming Language :: Python :: 3.10
Classifier: Programming Language :: Python :: 3.11
Classifier: Programming Language :: Python :: 3.12
Requires-Python: >=3.10
Requires-Dist: ecs-logging>=2
Requires-Dist: grpcio-tools<1.69,>=1.65
Requires-Dist: grpcio<1.69,>=1.65
Requires-Dist: protobuf<5.29,>=5.28
Requires-Dist: types-protobuf<5.29,>=5.28
Requires-Dist: uvloop<1,>=0.20
